{
 "macro": {
  "gender": 0,
  "age": 0.15,
  "asian": 1,
  "muscle": 0.5,
  "weight": 0.34,
  "height": 0.5,
  "proportions": 0.5
 },
 "modifiers": {
  "eyes/l-eye-scale-decr|incr": 0.559,
  "eyes/r-eye-scale-decr|incr": 0.559,
  "eyes/l-eye-height1-decr|incr": 0.899,
  "eyes/r-eye-height1-decr|incr": 0.899,
  "eyes/l-eye-height2-decr|incr": 0.3,
  "eyes/r-eye-height2-decr|incr": 0.3,
  "eyes/l-eye-trans-in|out": -0.1,
  "eyes/r-eye-trans-in|out": -0.1,
  "eyes/l-eye-trans-down|up": -0.18,
  "eyes/r-eye-trans-down|up": -0.18,
  "eyes/l-eye-epicanthus-in|out": -0.15,
  "eyes/r-eye-epicanthus-in|out": -0.15,
  "cheek/l-cheek-volume-decr|incr": -0.1,
  "cheek/r-cheek-volume-decr|incr": -0.1,
  "head/head-round": 0.27,
  "head/head-scale-vert-decr|incr": 0.713,
  "forehead/forehead-scale-vert-decr|incr": 0.2,
  "nose/nose-scale-vert-decr|incr": -0.22,
  "nose/nose-nostrils-width-decr|incr": -0.55,
  "nose/nose-scale-depth-decr|incr": -0.15,
  "chin/chin-height-decr|incr": -0.38,
  "chin/chin-prominent-decr|incr": -0.42,
  "chin/chin-bones-decr|incr": -0.28,
  "mouth/mouth-trans-down|up": 1,
  "mouth/mouth-scale-horiz-decr|incr": 0.649,
  "mouth/mouth-upperlip-volume-decr|incr": -0.4,
  "mouth/mouth-lowerlip-volume-decr|incr": -0.4,
  "mouth/mouth-upperlip-height-decr|incr": -0.9,
  "mouth/mouth-lowerlip-height-decr|incr": -0.7,
  "eyebrows/eyebrows-trans-down|up": 0.93,
  "mouth/mouth-scale-vert-decr|incr": 0.398,
  "nose/nose-scale-horiz-decr|incr": 0.233,
  "cheek/l-cheek-bones-decr|incr": -0.25,
  "cheek/r-cheek-bones-decr|incr": -0.25,
  "chin/chin-width-decr|incr": -0.3,
  "chin/chin-jaw-drop-decr|incr": -0.35,
  "chin/chin-prognathism-decr|incr": -0.15
 },
 "brow": "eyebrow007",
 "browRaise": 0.0155
}